FADiff/Elems.py
FADiff/FADiff.py
FADiff/FuncVect.py
FADiff/__init__.py
FADiff/fadUserCode.py
FADiff/revUserCode.py
FADiff/test_main.py
FADiff/fad/Gradients.py
FADiff/fad/Matrices.py
FADiff/fad/__init__.py
FADiff/rev/Gradients.py
FADiff/rev/Matrices.py
FADiff/rev/__init__.py
FADiff-0.19.dist-info/LICENSE.txt
FADiff-0.19.dist-info/METADATA
FADiff-0.19.dist-info/WHEEL
FADiff-0.19.dist-info/top_level.txt
FADiff-0.19.dist-info/RECORD
