Metadata-Version: 2.1
Name: FADiff
Version: 0.19
Summary: autodiff using forward and reverse mode
Home-page: https://github.com/liuxiaoxuan97/FADiff
Author: teamxvii
Author-email: UNKNOWN
License: MIT
Download-URL: https://github.com/liuxiaoxuan97/FADiff/archive/v_19.tar.gz
Keywords: autodiff,forward mode,reverse mode
Platform: UNKNOWN
Classifier: Development Status :: 3 - Alpha
Classifier: Intended Audience :: Developers
Classifier: Topic :: Software Development :: Build Tools
Classifier: License :: OSI Approved :: MIT License
Classifier: Programming Language :: Python :: 3
Classifier: Programming Language :: Python :: 3.4
Classifier: Programming Language :: Python :: 3.5
Classifier: Programming Language :: Python :: 3.6
Requires-Dist: numpy
Requires-Dist: pytest
Requires-Dist: coverage
